usercube/__init__.py
usercube/__main__.py
usercube/auth.py
usercube/constants.py
usercube-0.0.1.dev0.dist-info/WHEEL
usercube-0.0.1.dev0.dist-info/entry_points.txt
usercube-0.0.1.dev0.dist-info/METADATA
usercube-0.0.1.dev0.dist-info/RECORD
