Metadata-Version: 2.3
Name: usercube
Version: 0.0.1.dev0
Summary: The Usercube python client.
Requires-Dist: requests>=2.32.5
Requires-Python: >=3.12
